pyffp/__init__.py
pyffp/calc_footprint_FFP.py
pyffp/calc_footprint_FFP_climatology.py
pyffp/utils.py
pyffp-0.0.2.dist-info/LICENSE
pyffp-0.0.2.dist-info/METADATA
pyffp-0.0.2.dist-info/WHEEL
pyffp-0.0.2.dist-info/top_level.txt
pyffp-0.0.2.dist-info/RECORD
