Metadata-Version: 2.1
Name: pyffp
Version: 0.0.2
Summary: A simple two-dimensional parameterisation for Flux Footprint Prediction (FFP)
Author-email: Jemma Stachelek <jsta@lanl.gov>
Project-URL: Homepage, https://github.com/jsta/pyffp
Project-URL: Bug Tracker, https://github.com/jsta/pyffp/issues
Classifier: Programming Language :: Python :: 3
Classifier: License :: OSI Approved :: MIT License
Classifier: Operating System :: OS Independent
Requires-Python: >=3.7
License-File: LICENSE
